ezqc/__init__.py
ezqc/ac8.py
ezqc/blast.py
ezqc/color_print.py
ezqc/ezqc.py
ezqc/os7.py
ezqc/pbnc5.py
ezqc/pbsc3.py
ezqc/pbsq1.py
ezqc/psgc4.py
ezqc/psqs2.py
ezqc/sld6.py
ezqc-0.35.dist-info/LICENSE
ezqc-0.35.dist-info/METADATA
ezqc-0.35.dist-info/WHEEL
ezqc-0.35.dist-info/entry_points.txt
ezqc-0.35.dist-info/top_level.txt
ezqc-0.35.dist-info/RECORD
