Metadata-Version: 2.1
Name: ezqc
Version: 0.35
Summary: EZQC is a streamlined, terminal-based alternative to FastQC.
Author: Tinger Shi & Sky Li
License-File: LICENSE
Requires-Dist: numpy
Requires-Dist: matplotlib
Requires-Dist: pandas
Requires-Dist: scipy
Requires-Dist: Bio
